{
  "mcpServers": {
    "serena": {
      "type": "stdio",
      "command": "uvx",
      "args": [
        "--from",
        "git+https://github.com/oraios/serena",
        "serena-mcp-server",
        "--context",
        "ide-assistant",
        "--project",
        "./ISUCON"
      ],
      "env": {}
    },
    "github": {
      "command": "npx",
      "args": [
        "-y",
        "@modelcontextprotocol/server-github"
      ],
      "env": {
        "GITHUB_PERSONAL_ACCESS_TOKEN": "${GITHUB_PERSONAL_ACCESS_TOKEN}"
      }
    },
    "Context7": {
      "command": "npx",
      "args": [
        "-y",
        "@upstash/context7-mcp"
      ]
    },
    "deepwiki": {
      "command": "npx",
      "args": [
        "mcp-remote",
        "https://mcp.deepwiki.com/sse"
      ]
    },
    "playwright": {
      "type": "stdio",
      "command": "npx",
      "args": [
        "@playwright/mcp@latest",
        "--allowed-origins",
        "http://localhost:3000"
      ],
      "env": {}
    }
  }
}